[ {
  "tweetUrl" : "https://x.com/Web3WithBinance/status/1864520070820491691",
  "tweetId" : "1864520070820491691",
  "author" : "Web3WithBinance",
  "content" : "Daily priorities : \n\n Post GM \n Work",
  "hashtags" : [ ],
  "repliesCount" : "163",
  "retweetsCount" : "45",
  "likesCount" : "286",
  "createdAt" : "2024-12-05T04:00:00.000Z",
  "retweeters" : [ "7zuNc76jyF27973", "DJ_XSintrik", "Jonasro06043580", "kyiv_cryptopetr", "SunoMelodilerim", "piin878629", "NeokOlena", "StaceyM911", "web3Lyra", "0xpx97", "Tashiya_Simon", "givebackit", "BigAndMonsters", "cryptoder30", "RaselAl5", "minvesttech", "kraby_eth", "ShuaybGOAT", "EatYowSushi", "DEVANBDX869", "YusufGurses31", "crpt001", "GGhMONEY", "Munshi1553", "montes_tho22366", "UnicaRoberta", "LSymister5960", "AbolfazlBinance", "MusashiM2021" ]
}, {
  "tweetUrl" : "https://x.com/web3caer/status/1863700920975958520",
  "tweetId" : "1863700920975958520",
  "author" : "web3caer",
  "content" : "Buy xrp memes they said...",
  "hashtags" : [ ],
  "repliesCount" : "334",
  "retweetsCount" : "285",
  "likesCount" : "2.3K",
  "createdAt" : "2024-12-02T21:45:00.000Z",
  "retweeters" : [ "JasChowww", "bigbullsnow", "QVizzle", "domgiachetti", "CryptoVulture", "AlphaNFTBr", "JengoMongo96539", "matrody94", "khaldoggo69", "KnxwIxdge", "Roaring30s", "thesupremo69", "Corgil_", "TrippinDegen", "SlowRollinZeb", "SerBaggins", "BoomShakaLaka18", "thankuuverykind", "SOLFuru", "M8h_22", "gmidua98", "Kyo444nuit", "jo45263729", "_Reezo_", "darealHoodPapi", "0xvowl", "Moonshot_589", "scorpioblxck", "1BEASTonX", "alinap_official", "music_maga", "astrobuni", "ETHISTRASH", "hiinsle", "UncleCrypto23", "Theo_mwangi", "niakandela", "bach_troels", "Blankeyblanket", "dusty_crown", "Jimtheretrogamr", "Benito_Llan", "ogbame_justus", "mandrakemetal", "johnbilis89", "ferengidelity", "Heads_or_Tailes", "TravisHoltberg1", "LukeBlakley3", "taco_labs", "secretsauce777", "gem_detecter", "StrideVVS", "GamerGenieGG", "djkulls", "rad_dewd", "vokkerz", "urickbred101", "MoonShiller_", "Lost__Signal", "torontodominons", "Crypt0Emma", "Juliecooly_", "EfficioiVitae", "JorgeHi23368772", "esportsmobilee", "ErrantAvatar", "gee14g", "Jackworley77452", "ItsJesus95_", "Oleksan93684721", "defi0xlizard", "Infinity31492", "povertyanon", "baby_cripto", "degenspartanfan", "Zan24423926", "assiethee", "nseekak_", "SteeZoriuS", "SehsilCecil", "mfhanw3190", "Crypt0DegenzNFT", "CryptoWifPhat", "autismGCR", "lilsulung", "opalCnft", "supes12345", "chasingeureka", "SolSlimee", "RhysSOL", "gtooln", "Rama0x1", "stacktoodeeep", "BicturePig", "fytzearly", "CryptoiKhlout", "octoberCrypto", "FutureThirty", "DEGENMARRK", "gomegangfr", "kinseta", "FouseyDotEth", "PanPanjuL_", "dgenar8d", "chalat15", "setanimals", "69maxs", "colinstoltz", "Mydudest", "Pibby44", "SasoriKrueger", "Sango24931697", "TuFutur0", "ImbHunter", "MoreySurf7", "SamStonedIsland", "Odcryptos", "i_HoldCoin", "angelotti369", "Mike_Ess_", "NftDad_", "EmmaJamesTweet", "CryptoKev69", "RiccoRosas", "BernardChoo_", "gustavdegen", "tebayoso", "Biskupskifr", "Holdingtozero", "0xmisterb", "JeffDoncic", "web3caer", "rgr_park", "JcFrosti", "krodjr", "MakingPaperz", "rodshowZ", "0xmatrlx", "avaxoshi", "JonDanVan69", "0xMoses8", "bigbag420420", "RawMaterialNYC", "valueandtime", "slothquant", "ZLRtrades", "ExplorerFi", "MagaTrump24a", "MintologyMedia", "RafaelAerilyn", "10xrecruit22602", "lamrepum", "insiderforyou17", "FrogBullFaSho", "iLikeCrypto", "Oskar_Mot", "lamafiadegens", "adam_561", "Cryptilt", "pinkape217", "KyranLaCross", "YajSkywalker", "bullfrog69420", "cowlz_eth", "PoppaShepski", "cyberpaun" ]
}, {
  "tweetUrl" : "https://x.com/Filecoin/status/1863635604669423879",
  "tweetId" : "1863635604669423879",
  "author" : "Filecoin",
  "content" : "#FILBangalore is back! Join \n@Huddle01com\n and #Filecoin for India’s top blockchain conference featuring keynotes, workshops, panels, and more.\n\n Dec 6th, 2024\n\nLimited seats – register now: https://fil-bangalore.io",
  "hashtags" : [ "#Filecoin", "#FILBangalore" ],
  "repliesCount" : "11",
  "retweetsCount" : "44",
  "likesCount" : "284",
  "createdAt" : "2024-12-02T17:25:27.000Z",
  "retweeters" : [ "myeongjong65452", "Ximander1", "BIG_O_XRP1", "New00x00", "Haige2299", "Kanunsaivisions", "AverageGuyJames", "JulioMe60000182", "Safibarech41", "_yuji777", "Filliquid_kr", "caldera_in", "Crypto__Vee", "bitcoincyp1872", "Krijeev", "Ethereumlayer1", "dhavalgor0", "amssimoes", "UnNFTCollector", "cocacurt", "dollars143", "Solpok21", "DodiTobi", "FileLatam", "triapri17029384", "TiagoAlexCrypto", "selvaprakathees", "bart87404545", "felixcepeda8", "MPiotr1234", "Sanjeev44387651", "mamacit79255882", "Prmmehmet47", "iamcryptogunner", "kujireek", "lehuutai92kdbh", "cfxfilportalarb", "huddle01com", "1WideWorld", "emerakamoto" ]
}, {
  "tweetUrl" : "https://x.com/web3G_/status/1865471194276761749",
  "tweetId" : "1865471194276761749",
  "author" : "web3G_",
  "content" : "Dope shiiiiiiii",
  "hashtags" : [ ],
  "repliesCount" : "1",
  "retweetsCount" : "",
  "likesCount" : "1",
  "createdAt" : "2024-12-07T18:59:26.000Z",
  "retweeters" : [ ]
}, {
  "tweetUrl" : "https://x.com/CoinListingBot/status/1862413551073173614",
  "tweetId" : "1862413551073173614",
  "author" : "CoinListingBot",
  "content" : "New listing on #BTSE  https://btse.com/en/?ref=00W3Zz1Q…\nCoin: $URO\nPairs:\n#URO/#USD\n#URO/#USDT\n#newcoinlisting #crypto #cryptonews #cryptoAlerts #altcoins #bitcoin #blockchain #cryptocurrency #cryptotrading",
  "hashtags" : [ "#cryptotrading", "#USDT", "#MOZ", "#BTSE", "#crypto", "#newcoinlisting", "#blockchain", "#bitcoin", "#USD", "#cryptocurrency", "#cryptonews", "#GateIo", "#altcoins", "#URO", "#cryptoAlerts" ],
  "repliesCount" : "",
  "retweetsCount" : "",
  "likesCount" : "3",
  "createdAt" : "2024-11-29T08:29:27.000Z",
  "retweeters" : [ ]
} ]