[ {
  "tweetUrl" : "https://x.com/TechDev_52/status/1808843481504166337",
  "tweetId" : "1808843481504166337",
  "author" : "TechDev_52",
  "content" : "#Bitcoin",
  "hashtags" : [ "#Bitcoin", "#HODL" ],
  "repliesCount" : "432",
  "retweetsCount" : "2.2K",
  "likesCount" : "9.2K",
  "createdAt" : "2024-07-04T12:41:07.000Z",
  "retweeters" : [ "connor_joe42554", "DrakeJames51402", "manlove47666", "refuseniksproud", "DelwynEsse", "olajide1571403", "Prodiweb3", "Herbert_Termux", "Eckorock123", "kevyncraft1", "JohnAlbert73", "alisaa_pikapika", "01nickylove_", "EveePeriset", "Domina_diosa_35", "tomjame19018981", "Darman1177546", "freedomjackk", "aramamiscrypto", "RandySuhendar16", "funds_recover11", "0xGreensecret", "AreaCrypto89916", "tommyg8763", "Goodfounda34155", "plan4Retrive", "Jacksonpeter37", "QueenCryptoBTC", "Alisapikae", "bycryptoby", "tom_tomcollins", "higher32686", "web3_refunds", "jamescord128080", "nadiul11", "SergenUtkudemir", "Code2211H", "Leocryptogems", "100xCryptoGems_", "ampeonyz", "MRevena10454", "rubyyreidxo_01", "banidoDoTwitt3r", "rayaweb3", "LucasWilli62291", "Bitlanger", "landscape297627", "jetman1029734", "EstherJohn99250" ]
} ]