[ {
  "tweetUrl" : "https://x.com/BMTheEquityDesk/status/1865423046300889319",
  "tweetId" : "1865423046300889319",
  "author" : "BMTheEquityDesk",
  "content" : "Govt. को यह सब चीज़ के लिए खुल्ले दिमाग़ से देखना चाहिए। #Bitcoin",
  "hashtags" : [ "#Bitcoin" ],
  "repliesCount" : "115",
  "retweetsCount" : "82",
  "likesCount" : "730",
  "createdAt" : "2024-12-07T15:48:06.000Z",
  "retweeters" : [ "Hinduneu", "tim60091", "PRAVIN_TERSE", "moinsrcr", "shilpi621171540", "JasbirS08735830", "krdave", "spktodeepak", "india_boxoffice", "Ven1Prasad" ]
} ]