[ {
  "profileUrl" : "https://x.com/dotiryaki",
  "userId" : "dotiryaki",
  "userName" : "Doruk Tiryaki",
  "bio" : "Building \n@thunderbyFuel\n | University of California San Diego MBA | surfer",
  "profileImageUrl" : "",
  "followersCount" : "134.5K",
  "followingCount" : "294",
  "tweetCount" : 0,
  "tweets" : null,
  "following" : [ "tedoksan", "ecehanyildirim", "saliencexbt", "KriptoMevsimi", "ahmetvpoyraz", "umutak47shawty", "BCCTurkce", "SankoGameCorp", "WolfMS_", "excalibur34tr", "EfloudTheSurfer", "senyeth", "smoketheticker", "ArjunKalsy", "gmgiray", "ozgekeskin_", "CanOzsuerX", "DoganEth", "Cryptotalees", "Emreislek", "KardesBaris", "GokhanGark", "contextTRcrypto", "cryptotrfacts", "hirozaki2020", "CryptoKemal", "kerimcalender", "traderomercan", "ilkomilkoo", "omerdemircrypto", "Husslin_", "TheBullduck", "barisbuyuktas", "Spectura", "cberktavsan", "KarasuFt" ]
}, {
  "profileUrl" : "https://x.com/tommyshelbytr35",
  "userId" : "tommyshelbytr35",
  "userName" : "TommyShelby",
  "bio" : "Since January 2017 Crypto | FA | Former \n@CapitalVendetta\n Crypto Investment Specialist",
  "profileImageUrl" : "",
  "followersCount" : "773",
  "followingCount" : "200",
  "tweetCount" : 0,
  "tweets" : null,
  "following" : [ "dorukismen", "leonbozo1", "MuratMmturk", "AltaTradingTM", "dotiryaki", "Dondare5", "HASOsyalmedya", "xtradering", "nftmufettisi", "canincebusiness", "BOZMOZY", "EfloudTheSurfer", "fidelitas_lex", "ToksEmlakDeniz", "ekonomikocu", "KriptoDmr", "kmfg2021", "resenblock", "TobbyKitty", "TechCharts", "hedge__x", "HEG__", "DoganEth", "KardesBaris", "GokhanGark", "contextTRcrypto", "hirozaki2020", "TurkElit", "SantManukyan", "Dappadofficial", "ApocalypsePA", "tufanpoyrazz", "TheBullduck", "akincnr", "ustadsplinter34", "burak_tamac" ]
}, {
  "profileUrl" : "https://x.com/0xExumera",
  "userId" : "0xExumera",
  "userName" : "Exumera",
  "bio" : "Web3 Team•  \n@KonohaCrypt0\n @word4zz\nBuilding • \n@CactusVerseNFT\nDM for business ",
  "profileImageUrl" : "",
  "followersCount" : "13.3K",
  "followingCount" : "1,789",
  "tweetCount" : 0,
  "tweets" : null,
  "following" : [ "LetterApe", "AlphaShillApe", "killaclubsui", "the_empirex_", "RebelSocietyBTC", "Gtreaz4258", "MEET48ai", "RuyuiStudios", "janichain_lol", "mayki_nftnew", "btcFRU", "mushionsolana", "NatasKnights", "OrdiBoos", "hodl_ventures", "PyPyBera", "Onyx_sei", "madskulls01", "AZ_ON_APE", "Mrgusadventure", "playgoatgaming", "4UAICrypto", "NeoTokyoCode", "kongamilabs", "MasksOnApe", "monkidotfun", "thememevers", "SeimfersNFT", "MooncoinSVM", "Froginsville", "rillaboltclub", "apemaxib", "susan", "PrimalOnApe", "clintsealwood", "Creepy_Clownn", "clashofcoins" ]
}, {
  "profileUrl" : "https://x.com/borsacipowell",
  "userId" : "borsacipowell",
  "userName" : "powell's portfolio",
  "bio" : "#TRUMP\n#TRUMPVANCE\n#USA\n#NASDAQ100\n#ethereum\n\nyazilarim yatirim tavsiyesi değildir!",
  "profileImageUrl" : "",
  "followersCount" : "547",
  "followingCount" : "562",
  "tweetCount" : 0,
  "tweets" : null,
  "following" : [ "_ErkanOz", "GlobalCoinHub", "SamBarrieGO", "DavidSacks", "fenomensikici4", "umutak47shawty", "berk_ucmaz", "kriptogundemi", "aycaltunay", "CryptoSamettt", "thexcapitalist", "Sherlockwhale", "EarningsHubHQ", "DimaZeniuk", "doguknmn", "traderhamza", "DUALIPA", "Oculustrade", "Ayelet__Shaked", "mkristinesmith", "unusual_whales", "srkntnyldz", "TradesBerserk", "investmentHan", "RoarWeb3", "sugarCTO", "ether_fi_Fdn", "cperruna", "timolehes", "hedgefundguy3", "OneWifo", "IvanaSpear", "SirMemeAlot_Ai", "ozgurisil", "glamfilesx", "Honeystocks1" ]
}, {
  "profileUrl" : "https://x.com/norbelfc",
  "userId" : "norbelfc",
  "userName" : "norbel",
  "bio" : "Engineer  Sorare manager since 2021. Sign up & earn together w/ me from the link below:   Football - Crypto - NBA. Not financial advice",
  "profileImageUrl" : "",
  "followersCount" : "819",
  "followingCount" : "159",
  "tweetCount" : 0,
  "tweets" : null,
  "following" : [ "SorareNBALive", "Spectral_Labs", "gitcoin", "AltcoinView", "kartalisthaber", "uzmancoin", "solana", "saylor", "somewheresy", "Vanarchain", "VaultVera", "cz_binance", "Fetch_ai", "OuterscopeAI", "khouuba", "herseynba", "Selcoin", "odtublockchain", "Investingcom", "emirusahin", "borassorare", "shark5677", "McBrideAce", "Emreislek", "elonmusk", "cylefam", "VaultTerminal", "The_real_Gio", "fricthefrog", "timothysykes", "pin_trader", "aibyte_x", "SorareStrats", "0xSonicLabs", "MinaProtocol" ]
} ]